Workbook

Sheet 1_Immobilien
A1: Eigentümer | B1: Anteil % | C1: Objekt-ID | D1: Adresse | E1: PLZ | F1: Ort | G1: WE | H1: m² | I1: Kaltmiete/Mon | J1: NK/Mon | K1: Verkehrswert | L1: Kaufpreis | M1: Kaufjahr | N1: EK eingesetzt | O1: Status | P1: Marktmiete/m² | Q1: Jahres-Kaltmiete | R1: Brutto-Rendite | S1: Miete anteilig | T1: Wert anteilig | U1: EK anteilig | V1: Mietpotenzial/Mon | W1: Instandh.rücklage/Mon
A2: Felix Wanner | B2: 100 | C2: 1001_001 | D2: Gmünder Straße 11 | E2: 73540 | F2: Heubach | G2: 3 | H2: 245 | I2: 2433 | J2: 548 | K2: 583920 | L2: 380000 | M2: 2015 | N2: 95000 | O2: Vermietet | P2: 10.5 | Q2: =I2*12 -> 29196 | R2: =IF(K2>0,Q2/K2,0) -> 0.05 | S2: =I2*B2/100 -> 2433 | T2: =K2*B2/100 -> 583920 | U2: =N2*B2/100 -> 95000 | V2: =MAX(0,(P2*H2)-I2)*B2/100 -> 139.5 | W2: =H2*10/12*B2/100 -> 204.16667
A3: Felix Wanner | B3: 100 | C3: 1001_002 | D3: Eutighofer Straße 22 | E3: 73525 | F3: Schwäbisch Gmünd | G3: 6 | H3: 344 | I3: 2790 | J3: 552 | K3: 792000 | L3: 480000 | M3: 2016 | N3: 60000 | O3: 1 Leerstand | P3: 9.5 | Q3: =I3*12 -> 33480 | R3: =IF(K3>0,Q3/K3,0) -> 0.042272727 | S3: =I3*B3/100 -> 2790 | T3: =K3*B3/100 -> 792000 | U3: =N3*B3/100 -> 60000 | V3: =MAX(0,(P3*H3)-I3)*B3/100 -> 478 | W3: =H3*10/12*B3/100 -> 286.66667
A4: Felix Wanner | B4: 100 | C4: 1001_003 | D4: Jakob-Uhlmann-Str. 6 EG | E4: 73540 | F4: Heubach | G4: 1 | H4: 45 | I4: 450 | J4: 100 | K4: 118800 | L4: 55000 | M4: 2020 | N4: 10000 | O4: Vermietet | P4: 10 | Q4: =I4*12 -> 5400 | R4: =IF(K4>0,Q4/K4,0) -> 0.045454545 | S4: =I4*B4/100 -> 450 | T4: =K4*B4/100 -> 118800 | U4: =N4*B4/100 -> 10000 | V4: =MAX(0,(P4*H4)-I4)*B4/100 -> 0 | W4: =H4*10/12*B4/100 -> 37.5
A5: Felix Wanner | B5: 100 | C5: 1001_004 | D5: Jakob-Uhlmann-Str. 6 DG | E5: 73540 | F5: Heubach | G5: 1 | H5: 60 | I5: 580 | J5: 80 | K5: 153120 | L5: 58000 | M5: 2022 | N5: 10000 | O5: Vermietet | P5: 10 | Q5: =I5*12 -> 6960 | R5: =IF(K5>0,Q5/K5,0) -> 0.045454545 | S5: =I5*B5/100 -> 580 | T5: =K5*B5/100 -> 153120 | U5: =N5*B5/100 -> 10000 | V5: =MAX(0,(P5*H5)-I5)*B5/100 -> 20 | W5: =H5*10/12*B5/100 -> 50
A6: Felix Wanner | B6: 100 | C6: 1001_005 | D6: Schillerstraße 1 | E6: 73540 | F6: Heubach | G6: 1 | H6: 47 | I6: 564 | J6: 200 | K6: 137544 | L6: 60000 | M6: 2022 | N6: 10000 | O6: Vermietet | P6: 12 | Q6: =I6*12 -> 6768 | R6: =IF(K6>0,Q6/K6,0) -> 0.049206072 | S6: =I6*B6/100 -> 564 | T6: =K6*B6/100 -> 137544 | U6: =N6*B6/100 -> 10000 | V6: =MAX(0,(P6*H6)-I6)*B6/100 -> 0 | W6: =H6*10/12*B6/100 -> 39.166667
A7: Felix Wanner | B7: 100 | C7: 1001_006 | D7: Rembrandtweg 8 Wng. 23 | E7: 89520 | F7: Heidenheim | G7: 1 | H7: 77.45 | I7: 462.37 | J7: 336.74 | K7: 122066 | L7: 85000 | M7: 2016 | N7: 15000 | O7: Vermietet | P7: 8 | Q7: =I7*12 -> 5548.44 | R7: =IF(K7>0,Q7/K7,0) -> 0.045454426 | S7: =I7*B7/100 -> 462.37 | T7: =K7*B7/100 -> 122066 | U7: =N7*B7/100 -> 15000 | V7: =MAX(0,(P7*H7)-I7)*B7/100 -> 157.23 | W7: =H7*10/12*B7/100 -> 64.541667
A8: Felix Wanner | B8: 100 | C8: 1001_007 | D8: Rembrandtweg 8 Wng. 24 | E8: 89520 | F8: Heidenheim | G8: 1 | H8: 77.45 | I8: 650 | J8: 270 | K8: 171600 | L8: 95000 | M8: 2016 | N8: 15000 | O8: Vermietet | P8: 8.5 | Q8: =I8*12 -> 7800 | R8: =IF(K8>0,Q8/K8,0) -> 0.045454545 | S8: =I8*B8/100 -> 650 | T8: =K8*B8/100 -> 171600 | U8: =N8*B8/100 -> 15000 | V8: =MAX(0,(P8*H8)-I8)*B8/100 -> 8.325 | W8: =H8*10/12*B8/100 -> 64.541667
A9: Felix Wanner | B9: 100 | C9: 1001_008 | D9: Rembrandtweg 8 Wng. 32 | E9: 89520 | F9: Heidenheim | G9: 1 | H9: 82 | I9: 492 | J9: 323 | K9: 129888 | L9: 90000 | M9: 2016 | N9: 15000 | O9: Vermietet | P9: 8 | Q9: =I9*12 -> 5904 | R9: =IF(K9>0,Q9/K9,0) -> 0.045454545 | S9: =I9*B9/100 -> 492 | T9: =K9*B9/100 -> 129888 | U9: =N9*B9/100 -> 15000 | V9: =MAX(0,(P9*H9)-I9)*B9/100 -> 164 | W9: =H9*10/12*B9/100 -> 68.333333
A10: Felix Wanner | B10: 100 | C10: 1001_009 | D10: Oberbettringer Str. 73/1 | E10: 73525 | F10: Schwäbisch Gmünd | G10: 1 | H10: 85 | I10: 0 | J10: 0 | K10: 211200 | L10: 180000 | M10: 2023 | N10: 180000 | O10: Leerstand | P10: 10 | Q10: =I10*12 -> 0 | R10: =IF(K10>0,Q10/K10,0) -> 0 | S10: =I10*B10/100 -> 0 | T10: =K10*B10/100 -> 211200 | U10: =N10*B10/100 -> 180000 | V10: =MAX(0,(P10*H10)-I10)*B10/100 -> 850 | W10: =H10*10/12*B10/100 -> 70.833333
A11: FW + JW | B11: 100 | C11: 1001_010 | D11: Kirchplatz 8 (Eigenheim) | E11: 73563 | F11: Mögglingen | G11: 1 | H11: 150 | I11: 0 | J11: 0 | K11: 600000 | L11: 480000 | M11: 2021 | N11: 80000 | O11: Eigennutz | P11: 0 | Q11: =I11*12 -> 0 | R11: =IF(K11>0,Q11/K11,0) -> 0 | S11: =I11*B11/100 -> 0 | T11: =K11*B11/100 -> 600000 | U11: =N11*B11/100 -> 80000 | V11: =MAX(0,(P11*H11)-I11)*B11/100 -> 0 | W11: =H11*10/12*B11/100 -> 125
A12: Jasmin Wanner | B12: 100 | C12: 1005_001 | D12: Steinertgasse 5B Wng. 51 | E12: 73434 | F12: Aalen | G12: 1 | H12: 40 | I12: 300 | J12: 160 | K12: 79200 | L12: 37500 | M12: 2017 | N12: 5000 | O12: Vermietet | P12: 8.5 | Q12: =I12*12 -> 3600 | R12: =IF(K12>0,Q12/K12,0) -> 0.045454545 | S12: =I12*B12/100 -> 300 | T12: =K12*B12/100 -> 79200 | U12: =N12*B12/100 -> 5000 | V12: =MAX(0,(P12*H12)-I12)*B12/100 -> 40 | W12: =H12*10/12*B12/100 -> 33.333333
A13: FW+SK eGbR | B13: 50 | C13: 1003_001 | D13: Stauffenbergstraße 30 | E13: 73431 | F13: Aalen | G13: 9 | H13: 636 | I13: 4932 | J13: 1072 | K13: 1269191 | L13: 650000 | M13: 2017 | N13: 100000 | O13: Vermietet | P13: 9 | Q13: =I13*12 -> 59184 | R13: =IF(K13>0,Q13/K13,0) -> 0.046631279 | S13: =I13*B13/100 -> 2466 | T13: =K13*B13/100 -> 634595.5 | U13: =N13*B13/100 -> 50000 | V13: =MAX(0,(P13*H13)-I13)*B13/100 -> 396 | W13: =H13*10/12*B13/100 -> 265
... A18: WK II eGbR | B18: 50 | C18: 1004_004-008 | D18: Stauffenbergring 28 (5 WE) | E18: 73479 | F18: Ellwangen | G18: 5 | H18: 347.76 | I18: 2470 | J18: 603 | K18: 760200 | L18: 705000 | M18: 2024 | N18: 50000 | O18: Vermietet | P18: 9 | Q18: =I18*12 -> 29640 | R18: =IF(K18>0,Q18/K18,0) -> 0.03898974 | S18: =I18*B18/100 -> 1235 | T18: =K18*B18/100 -> 380100 | U18: =N18*B18/100 -> 25000 | V18: =MAX(0,(P18*H18)-I18)*B18/100 -> 329.92 | W18: =H18*10/12*B18/100 -> 144.9
A19: SUMME (anteilig) | G19: =SUMPRODUCT(G2:G18,B2:B18/100) -> 29.5 | H19: =SUMPRODUCT(H2:H18,B2:B18/100) -> 2048.98 | I19: =SUM(S2:S18) -> 15011.87 | K19: =SUM(T2:T18) -> 4797667 | N19: =SUM(U2:U18) -> 625000 | Q19: =I19*12 -> 180142.44 | R19: =IF(K19>0,Q19/K19,0) -> 0.037547925 | V19: =SUM(V2:V18) -> 2828.775 | W19: =SUM(W2:W18) -> 1707.4833

Sheet 2_Darlehen
A1: Eigentümer | B1: Anteil % | C1: Objekt | D1: Bank | E1: IBAN/Konto | F1: Beginn | G1: Ursprung | H1: Saldo aktuell | I1: Rate/Mon | J1: Zins % | K1: Ende Zinsbind. | L1: Getilgt | M1: Tilg.quote % | N1: Zinsaufw./Jahr | O1: Saldo anteilig | P1: Rate anteilig | Q1: Bemerkung
A2: Felix Wanner | B2: 100 | C2: Gmünder Str. 11 | D2: Raiba Rosenstein | E2: DE90 6136 1722 0087 2592 06 | F2: 01.11.2015 | G2: 115000 | H2: 87007.64 | I2: 400 | J2: 0.0195 | K2: 30.11.2025 | L2: =G2-H2 -> 27992.36 | M2: =IF(G2>0,L2/G2,0) -> 0.24341183 | N2: =H2*J2 -> 1696.649 | O2: =H2*B2/100 -> 87007.64 | P2: =I2*B2/100 -> 400
A3: Felix Wanner | B3: 100 | C3: Gmünder Str. 11 | D3: Raiba Rosenstein | E3: DE27 6136 1722 0087 2592 73 | F3: 01.09.2019 | G3: 100000 | H3: 100000 | I3: 133.33 | J3: 0.016 | K3: 30.09.2029 | L3: =G3-H3 -> 0 | M3: =IF(G3>0,L3/G3,0) -> 0 | N3: =H3*J3 -> 1600 | O3: =H3*B3/100 -> 100000 | P3: =I3*B3/100 -> 133.33 | Q3: Tilgungsersatz UnionDepot
A4: Felix Wanner | B4: 100 | C4: Gmünder Str. 11 | D4: MünchenerHyp | E4: 1131802400 | F4: 01.11.2015 | G4: 150000 | H4: 102393.05 | I4: 691.5 | J4: 0.0268 | K4: 31.12.2040 | L4: =G4-H4 -> 47606.95 | M4: =IF(G4>0,L4/G4,0) -> 0.31737967 | N4: =H4*J4 -> 2744.1337 | O4: =H4*B4/100 -> 102393.05 | P4: =I4*B4/100 -> 691.5
A5: Felix Wanner | B5: 100 | C5: Eutighofer Str. 22 | D5: Raiba Rosenstein | E5: DE49 6136 1722 0087 2592 65 | F5: 01.08.2016 | G5: 195000 | H5: 132207 | I5: 805 | J5: 0.018 | K5: 30.08.2026 | L5: =G5-H5 -> 62793 | M5: =IF(G5>0,L5/G5,0) -> 0.32201538 | N5: =H5*J5 -> 2379.726 | O5: =H5*B5/100 -> 132207 | P5: =I5*B5/100 -> 805
A6: Felix Wanner | B6: 100 | C6: Eutighofer Str. 22 | D6: Raiba Rosenstein | E6: DE05 6136 1722 0087 2592 81 | F6: 01.11.2016 | G6: 100000 | H6: 59918.22 | I6: 880 | J6: 0.012 | K6: 30.11.2026 | L6: =G6-H6 -> 40081.78 | M6: =IF(G6>0,L6/G6,0) -> 0.4008178 | N6: =H6*J6 -> 719.01864 | O6: =H6*B6/100 -> 59918.22 | P6: =I6*B6/100 -> 880
A7: Felix Wanner | B7: 100 | C7: Eutighofer Str. 22 | D7: MünchenerHyp | E7: 1133479400 | F7: 01.08.2016 | G7: 190000 | H7: 164621.37 | I7: 680.52 | J7: 0.023 | K7: 31.08.2046 | L7: =G7-H7 -> 25378.63 | M7: =IF(G7>0,L7/G7,0) -> 0.13357174 | N7: =H7*J7 -> 3786.2915 | O7: =H7*B7/100 -> 164621.37 | P7: =I7*B7/100 -> 680.52
A8: Felix Wanner | B8: 100 | C8: Eutighofer Str. 22 | D8: KSK Ostalb | E8: DE03 6145 0050 6241 1072 92 | F8: 01.01.2020 | G8: 50000 | H8: 21433.57 | I8: 500 | J8: 0.015 | K8: 01.01.2030 | L8: =G8-H8 -> 28566.43 | M8: =IF(G8>0,L8/G8,0) -> 0.5713286 | N8: =H8*J8 -> 321.50355 | O8: =H8*B8/100 -> 21433.57 | P8: =I8*B8/100 -> 500
A9: Felix Wanner | B9: 100 | C9: Jakob-Uhlmann 6 EG | D9: KSK Ostalb | E9: DE84 6145 0050 6241 1639 37 | F9: 01.07.2020 | G9: 55000 | H9: 47405.2 | I9: 203.96 | J9: 0.0195 | K9: 01.07.2030 | L9: =G9-H9 -> 7594.8 | M9: =IF(G9>0,L9/G9,0) -> 0.13808727 | N9: =H9*J9 -> 924.4014 | O9: =H9*B9/100 -> 47405.2 | P9: =I9*B9/100 -> 203.96
A10: Felix Wanner | B10: 100 | C10: Jakob-Uhlmann 6 DG | D10: Raiba Rosenstein | E10: DE46 6136 1722 0087 2592 22 | F10: 01.06.2022 | G10: 28000 | H10: 17093.18 | I10: 137.9 | J10: 0.0225 | K10: 30.06.2026 | L10: =G10-H10 -> 10906.82 | M10: =IF(G10>0,L10/G10,0) -> 0.38952929 | N10: =H10*J10 -> 384.59655 | O10: =H10*B10/100 -> 17093.18 | P10: =I10*B10/100 -> 137.9
A11: Felix Wanner | B11: 100 | C11: Jakob-Uhlmann 6 DG | D11: BSV Schwäb. Hall | E11: 24402962J01 | F11: 01.06.2022 | G11: 29955 | H11: 29955 | I11: 145 | J11: 0.0225 | K11: 30.06.2026 | L11: =G11-H11 -> 0 | M11: =IF(G11>0,L11/G11,0) -> 0 | N11: =H11*J11 -> 673.9875 | O11: =H11*B11/100 -> 29955 | P11: =I11*B11/100 -> 145 | Q11: BSV Guthaben: 10.544,68€
A12: Felix Wanner | B12: 100 | C12: Schillerstraße 1 | D12: Raiba Rosenstein | E12: DE24 6136 1722 0087 2592 30 | F12: 01.06.2022 | G12: 30000 | H12: 19932.82 | I12: 135 | J12: 0.0225 | K12: 30.06.2026 | L12: =G12-H12 -> 10067.18 | M12: =IF(G12>0,L12/G12,0) -> 0.33557267 | N12: =H12*J12 -> 448.48845 | O12: =H12*B12/100 -> 19932.82 | P12: =I12*B12/100 -> 135
A13: Felix Wanner | B13: 100 | C13: Schillerstraße 1 | D13: BSV Schwäb. Hall | E13: 24402962J02 | F13: 01.06.2022 | G13: 29955 | H13: 29955 | I13: 135 | J13: 0.0225 | K13: 30.06.2026 | L13: =G13-H13 -> 0 | M13: =IF(G13>0,L13/G13,0) -> 0 | N13: =H13*J13 -> 673.9875 | O13: =H13*B13/100 -> 29955 | P13: =I13*B13/100 -> 135 | Q13: BSV Guthaben: 10.009,80€
A14: Felix Wanner | B14: 100 | C14: Rembrandtweg 8 (3 WE) | D14: Raiba Rosenstein | E14: DE93 6136 1722 0087 2592 49 | F14: 01.07.2016 | G14: 108000 | H14: 72225.55 | I14: 465.3 | J14: 0.0195 | K14: 30.07.2026 | L14: =G14-H14 -> 35774.45 | M14: =IF(G14>0,L14/G14,0) -> 0.33124491 | N14: =H14*J14 -> 1408.3982 | O14: =H14*B14/100 -> 72225.55 | P14: =I14*B14/100 -> 465.3
A15: Felix Wanner | B15: 100 | C15: Rembrandtweg 8 (3 WE) | D15: Raiba Rosenstein | E15: DE53 6136 1722 0087 2592 90 | F15: 01.07.2016 | G15: 50000 | H15: 30288.59 | I15: 440 | J15: 0.012 | K15: 30.11.2026 | L15: =G15-H15 -> 19711.41 | M15: =IF(G15>0,L15/G15,0) -> 0.3942282 | N15: =H15*J15 -> 363.46308 | O15: =H15*B15/100 -> 30288.59 | P15: =I15*B15/100 -> 440
A16: Felix Wanner | B16: 100 | C16: Rembrandtweg 8 (3 WE) | D16: MünchenerHyp | E16: 1133198400 | F16: 01.07.2016 | G16: 110000 | H16: 76095.7 | I16: 486.11 | J16: 0.0228 | K16: 30.06.2041 | L16: =G16-H16 -> 33904.3 | M16: =IF(G16>0,L16/G16,0) -> 0.30822091 | N16: =H16*J16 -> 1734.982 | O16: =H16*B16/100 -> 76095.7 | P16: =I16*B16/100 -> 486.11
A17: FW + JW | B17: 100 | C17: Kirchplatz 8 (Eigenheim) | D17: Raiba Rosenstein | E17: DE38 6136 1722 0092 2632 08 | F17: 01.03.2021 | G17: 300000 | H17: 273018.57 | I17: 696.29 | J17: 0.0096 | K17: 30.03.2031 | L17: =G17-H17 -> 26981.43 | M17: =IF(G17>0,L17/G17,0) -> 0.0899381 | N17: =H17*J17 -> 2620.9783 | O17: =H17*B17/100 -> 273018.57 | P17: =I17*B17/100 -> 696.29
A18: FW + JW | B18: 100 | C18: Kirchplatz 8 (Eigenheim) | D18: MünchenerHyp | E18: 1143452400 | F18: 01.03.2021 | G18: 300000 | H18: 285394.06 | I18: 709.25 | J18: 0.0186 | K18: 28.02.2051 | L18: =G18-H18 -> 14605.94 | M18: =IF(G18>0,L18/G18,0) -> 0.048686467 | N18: =H18*J18 -> 5308.3295 | O18: =H18*B18/100 -> 285394.06 | P18: =I18*B18/100 -> 709.25
A19: Jasmin Wanner | B19: 100 | C19: Steinertgasse 5B | D19: Raiba Rosenstein | E19: DE74 6136 1722 0090 2372 00 | F19: 01.05.2017 | G19: 37500 | H19: 33406.63 | I19: 95 | J19: 0.019 | K19: 30.04.2027 | L19: =G19-H19 -> 4093.37 | M19: =IF(G19>0,L19/G19,0) -> 0.10915653 | N19: =H19*J19 -> 634.72597 | O19: =H19*B19/100 -> 33406.63 | P19: =I19*B19/100 -> 95
A20: FW+SK eGbR | B20: 50 | C20: Stauffenbergstr. 30 | D20: Raiba Rosenstein | E20: DE32 6136 1722 0090 1972 16 | F20: 27.04.2017 | G20: 650000 | H20: 494645.79 | I20: 2820 | J20: 0.021 | K20: 30.03.2027 | L20: =G20-H20 -> 155354.21 | M20: =IF(G20>0,L20/G20,0) -> 0.23900648 | N20: =H20*J20 -> 10387.562 | O20: =H20*B20/100 -> 247322.89 | P20: =I20*B20/100 -> 1410
A21: FW+SK eGbR | B21: 50 | C21: Stauffenbergstr. 33 | D21: Raiba Rosenstein | E21: DE54 6136 1722 0090 1972 08 | F21: 27.04.2017 | G21: 390000 | H21: 296055.06 | I21: 1700 | J21: 0.021 | K21: 30.03.2027 | L21: =G21-H21 -> 93944.94 | M21: =IF(G21>0,L21/G21,0) -> 0.24088446 | N21: =H21*J21 -> 6217.1563 | O21: =H21*B21/100 -> 148027.53 | P21: =I21*B21/100 -> 850
A22: FW+SK eGbR | B22: 50 | C22: Stauffenbergstr. 30+33 | D22: Raiba Rosenstein | E22: DE85 6136 1722 0090 1972 32 | F22: 03.07.2020 | G22: 280000 | H22: 245934 | I22: 1045 | J22: 0.0198 | K22: 30.06.2027 | L22: =G22-H22 -> 34066 | M22: =IF(G22>0,L22/G22,0) -> 0.12166429 | N22: =H22*J22 -> 4869.4932 | O22: =H22*B22/100 -> 122967 | P22: =I22*B22/100 -> 522.5 | Q22: Sanierung
A23: WK II eGbR | B23: 50 | C23: Silcherstr. 4 Wng. 8 | D23: Raiba Rosenstein | E23: DE91 6136 1722 0097 7562 37 | F23: 20.12.2022 | G23: 159000 | H23: 155741.77 | I23: 792.07 | J23: 0.0448 | K23: 15.12.2032 | L23: =G23-H23 -> 3258.23 | M23: =IF(G23>0,L23/G23,0) -> 0.020492013 | N23: =H23*J23 -> 6977.2313 | O23: =H23*B23/100 -> 77870.885 | P23: =I23*B23/100 -> 396.035
A24: WK II eGbR | B24: 50 | C24: Silcherstr. 4 Wng. 7 | D24: Raiba Rosenstein | E24: DE16 6136 1722 0097 7562 29 | F24: 20.12.2022 | G24: 106000 | H24: 103825.41 | I24: 528.23 | J24: 0.0448 | K24: 15.12.2032 | L24: =G24-H24 -> 2174.59 | M24: =IF(G24>0,L24/G24,0) -> 0.020515 | N24: =H24*J24 -> 4651.3784 | O24: =H24*B24/100 -> 51912.705 | P24: =I24*B24/100 -> 264.115
A25: WK II eGbR | B25: 50 | C25: Stauffenbergring 28 | D25: Raiba Rosenstein | E25: DE66 6136 1722 0097 7562 02 | F25: 29.10.2024 | G25: 705000 | H25: 705000 | I25: 2068 | J25: 0.0352 | K25: 30.11.2034 | L25: =G25-H25 -> 0 | M25: =IF(G25>0,L25/G25,0) -> 0 | N25: =H25*J25 -> 24816 | O25: =H25*B25/100 -> 352500 | P25: =I25*B25/100 -> 1034 | Q25: Tilgungsfrei bis 31.07.2026
A26: SUMME (anteilig) | G26: =SUMPRODUCT(G2:G25,B2:B25/100) -> 3123410 | H26: =SUM(O2:O25) -> 2582952.2 | I26: =SUM(P2:P25) -> 12215.81 | L26: =G26-H26 -> 540457.83 | M26: =IF(G26>0,L26/G26,0) -> 0.17303455 | N26: =SUMPRODUCT(N2:N25,B2:B25/100) -> 57383.071

Sheet 3_PV-Anlagen
A1: Eigentümer | B1: Anteil % | C1: Standort | D1: kWp | E1: Inbetriebnahme | F1: Bank | G1: IBAN | H1: Ursprung Darl. | I1: Saldo aktuell | J1: Einnahmen/Mon | K1: Rate/Mon | L1: Zins % | M1: Ende Zinsbind. | N1: Aktueller Wert | O1: Cashflow/Mon | P1: Cashflow/Jahr | Q1: Einnahmen anteilig | R1: Saldo anteilig | S1: Wert anteilig | T1: Bemerkung
A2: Felix Wanner | B2: 100 | C2: Milchstraße, Stade | D2: 240 | E2: 02/2020 | F2: VB Südwestfalen | G2: DE53 4476 1534 0016 1701 22 | H2: 344000 | I2: 344000 | J2: 2100 | K2: 487.33 | L2: 0.017 | M2: 28.02.2030 | N2: 240000 | O2: =(J2-K2)*B2/100 -> 1612.67 | P2: =O2*12 -> 19352.04 | Q2: =J2*B2/100 -> 2100 | R2: =I2*B2/100 -> 344000 | S2: =N2*B2/100 -> 240000 | T2: Tilgungsersatz R+V ca. 158.000€
A3: Wanner PV I GbR | B3: 50 | C3: Ackerköpfe 26, Mehrum | D3: 200 | E3: 12/2023 | F3: Raiba Rosenstein | G3: DE56 6136 1722 0099 2362 14 | H3: 300000 | I3: 277534.52 | J3: 1000 | K3: 2225 | L3: 0.057 | M3: 01.12.2033 | N3: 300000 | O3: =(J3-K3)*B3/100 -> -612.5 | P3: =O3*12 -> -7350 | Q3: =J3*B3/100 -> 500 | R3: =I3*B3/100 -> 138767.26 | S3: =N3*B3/100 -> 150000
A4: Felix Wanner | B4: 100 | C4: Grüner Weg, Rastede | D4: 400 | E4: 11/2024 | F4: VB Franken | G4: DE03 6746 1424 3312 9470 04 | H4: 344000 | I4: 343115.47 | J4: 1500 | K4: 2315 | L4: 0.0499 | M4: 30.11.2034 | N4: 344000 | O4: =(J4-K4)*B4/100 -> -815 | P4: =O4*12 -> -9780 | Q4: =J4*B4/100 -> 1500 | R4: =I4*B4/100 -> 343115.47 | S4: =N4*B4/100 -> 344000
A5: SUMME (anteilig) | D5: =SUMPRODUCT(D2:D4,B2:B4/100) -> 740 | H5: =SUMPRODUCT(H2:H4,B2:B4/100) -> 838000 | I5: =SUM(R2:R4) -> 825882.73 | J5: =SUM(Q2:Q4) -> 4100 | K5: =SUMPRODUCT(K2:K4,B2:B4/100) -> 3914.83 | N5: =SUM(S2:S4) -> 734000 | O5: =SUM(O2:O4) -> 185.17 | P5: =O5*12 -> 2222.04

Sheet 4_Cashflow_Detail
A1: Objekt | B1: Anteil % | C1: Kaltmiete/Mon | D1: NK/Mon | E1: Darlehensraten/Mon | F1: Instandh.rücklage/Mon | G1: Netto-Cashflow/Mon | H1: Netto-Cashflow/Jahr | I1: Cashflow anteilig/Mon | J1: Cashflow anteilig/Jahr | K1: EK-Rendite (geschätzt)
A2: Gmünder Str. 11 | B2: 100 | C2: 2433 | D2: 548 | E2: 1224.83 | F2: 204 | G2: =C2-E2-F2 -> 1004.17 | H2: =G2*12 -> 12050.04 | I2: =G2*B2/100 -> 1004.17 | J2: =I2*12 -> 12050.04 | K2: =IF(95000>0,J2/95000,"-") -> 0.12684253
A3: Eutighofer Str. 22 | B3: 100 | C3: 2790 | D3: 552 | E3: 2865.52 | F3: 287 | G3: =C3-E3-F3 -> -362.52 | H3: =G3*12 -> -4350.24 | I3: =G3*B3/100 -> -362.52 | J3: =I3*12 -> -4350.24 | K3: =IF(60000>0,J3/60000,"-") -> -0.072504
A4: Jakob-Uhlmann 6 EG | B4: 100 | C4: 450 | D4: 100 | E4: 203.96 | F4: 38 | G4: =C4-E4-F4 -> 208.04 | H4: =G4*12 -> 2496.48 | I4: =G4*B4/100 -> 208.04 | J4: =I4*12 -> 2496.48 | K4: =IF(10000>0,J4/10000,"-") -> 0.249648
A5: Jakob-Uhlmann 6 DG | B5: 100 | C5: 580 | D5: 80 | E5: 282.9 | F5: 50 | G5: =C5-E5-F5 -> 247.1 | H5: =G5*12 -> 2965.2 | I5: =G5*B5/100 -> 247.1 | J5: =I5*12 -> 2965.2 | K5: =IF(10000>0,J5/10000,"-") -> 0.29652
A6: Schillerstraße 1 | B6: 100 | C6: 564 | D6: 200 | E6: 270 | F6: 39 | G6: =C6-E6-F6 -> 255 | H6: =G6*12 -> 3060 | I6: =G6*B6/100 -> 255 | J6: =I6*12 -> 3060 | K6: =IF(10000>0,J6/10000,"-") -> 0.306
A7: Rembrandtweg 8 (3 WE) | B7: 100 | C7: 1604.37 | D7: 929.74 | E7: 1391.41 | F7: 197 | G7: =C7-E7-F7 -> 15.96 | H7: =G7*12 -> 191.52 | I7: =G7*B7/100 -> 15.96 | J7: =I7*12 -> 191.52 | K7: =IF(45000>0,J7/45000,"-") -> 0.004256
A8: Oberbettringer Str. 73/1 | B8: 100 | C8: 0 | D8: 0 | E8: 0 | F8: 71 | G8: =C8-E8-F8 -> -71 | H8: =G8*12 -> -852 | I8: =G8*B8/100 -> -71 | J8: =I8*12 -> -852 | K8: =IF(180000>0,J8/180000,"-") -> -0.0047333333
A9: Kirchplatz 8 (Eigenheim) | B9: 100 | C9: 0 | D9: 0 | E9: 1405.54 | F9: 125 | G9: =C9-E9-F9 -> -1530.54 | H9: =G9*12 -> -18366.48 | I9: =G9*B9/100 -> -1530.54 | J9: =I9*12 -> -18366.48 | K9: =IF(80000>0,J9/80000,"-") -> -0.229581
A10: Steinertgasse 5B (JW) | B10: 100 | C10: 300 | D10: 160 | E10: 95 | F10: 33 | G10: =C10-E10-F10 -> 172 | H10: =G10*12 -> 2064 | I10: =G10*B10/100 -> 172 | J10: =I10*12 -> 2064 | K10: =IF(5000>0,J10/5000,"-") -> 0.4128
A11: Stauffenbergstr. 30 | B11: 50 | C11: 4932 | D11: 1072 | E11: 2820 | F11: 530 | G11: =C11-E11-F11 -> 1582 | H11: =G11*12 -> 18984 | I11: =G11*B11/100 -> 791 | J11: =I11*12 -> 9492 | K11: =IF(100000>0,J11/100000,"-") -> 0.09492
A12: Stauffenbergstr. 33 | B12: 50 | C12: 3629 | D12: 830 | E12: 1700 | F12: 369 | G12: =C12-E12-F12 -> 1560 | H12: =G12*12 -> 18720 | I12: =G12*B12/100 -> 780 | J12: =I12*12 -> 9360 | K12: =IF(60000>0,J12/60000,"-") -> 0.156
A13: Stauffenbergstr. 30+33 Sanierung | B13: 50 | C13: 0 | D13: 0 | E13: 1045 | F13: 0 | G13: =C13-E13-F13 -> -1045 | H13: =G13*12 -> -12540 | I13: =G13*B13/100 -> -522.5 | J13: =I13*12 -> -6270 | K13: -
A14: Silcherstr. 4 Wng. 8 | B14: 50 | C14: 800 | D14: 200 | E14: 792.07 | F14: 63 | G14: =C14-E14-F14 -> -55.07 | H14: =G14*12 -> -660.84 | I14: =G14*B14/100 -> -27.535 | J14: =I14*12 -> -330.42 | K14: =IF(30000>0,J14/30000,"-") -> -0.011014
A15: Silcherstr. 4 Wng. 7 | B15: 50 | C15: 500 | D15: 60 | E15: 528.23 | F15: 35 | G15: =C15-E15-F15 -> -63.23 | H15: =G15*12 -> -758.76 | I15: =G15*B15/100 -> -31.615 | J15: =I15*12 -> -379.38 | K15: =IF(20000>0,J15/20000,"-") -> -0.018969
A16: Silcherstr. 2 Wng. 10 | B16: 50 | C16: 250 | D16: 70 | E16: 0 | F16: 39 | G16: =C16-E16-F16 -> 211 | H16: =G16*12 -> 2532 | I16: =G16*B16/100 -> 105.5 | J16: =I16*12 -> 1266 | K16: -
A17: Stauffenbergring 28 (5 WE) | B17: 50 | C17: 2470 | D17: 603 | E17: 2068 | F17: 290 | G17: =C17-E17-F17 -> 112 | H17: =G17*12 -> 1344 | I17: =G17*B17/100 -> 56 | J17: =I17*12 -> 672 | K17: =IF(50000>0,J17/50000,"-") -> 0.01344
A18: SUMME (anteilig) | C18: =SUMPRODUCT(C2:C17,B2:B17/100) -> 15011.87 | E18: =SUMPRODUCT(E2:E17,B2:B17/100) -> 12215.81 | F18: =SUMPRODUCT(F2:F17,B2:B17/100) -> 1707 | I18: =SUM(I2:I17) -> 1089.06 | J18: =I18*12 -> 13068.72

Sheet 5_AfA_Steuer
A1: STEUERLICHE ÜBERSICHT - AfA und Zinsaufwand
A3: Objekt | B3: Kaufpreis (anteilig) | C3: Gebäudeanteil % | D3: AfA-Satz % | E3: Kaufjahr | F3: Restnutzungsdauer | G3: AfA/Jahr | H3: Kum. AfA bis 2026
A4: Gmünder Str. 11 | B4: 380000 | C4: 0.8 | D4: 0.02 | E4: 2015 | F4: 40 | G4: =B4*C4*D4 -> 6080 | H4: =G4*(2026-E4) -> 66880
A5: Eutighofer Str. 22 | B5: 480000 | C5: 0.8 | D5: 0.02 | E5: 2016 | F5: 41 | G5: =B5*C5*D5 -> 7680 | H5: =G5*(2026-E5) -> 76800
A6: Jakob-Uhlmann 6 EG | B6: 55000 | C6: 0.8 | D6: 0.02 | E6: 2020 | F6: 45 | G6: =B6*C6*D6 -> 880 | H6: =G6*(2026-E6) -> 5280
A7: Jakob-Uhlmann 6 DG | B7: 58000 | C7: 0.8 | D7: 0.02 | E7: 2022 | F7: 47 | G7: =B7*C7*D7 -> 928 | H7: =G7*(2026-E7) -> 3712
A8: Schillerstraße 1 | B8: 60000 | C8: 0.8 | D8: 0.02 | E8: 2022 | F8: 47 | G8: =B8*C8*D8 -> 960 | H8: =G8*(2026-E8) -> 3840
A9: Rembrandtweg 8 (3 WE) | B9: 270000 | C9: 0.8 | D9: 0.02 | E9: 2016 | F9: 41 | G9: =B9*C9*D9 -> 4320 | H9: =G9*(2026-E9) -> 43200
A10: Oberbettringer Str. 73/1 | B10: 180000 | C10: 0.8 | D10: 0.02 | E10: 2023 | F10: 48 | G10: =B10*C10*D10 -> 2880 | H10: =G10*(2026-E10) -> 8640
A11: Kirchplatz 8 (Eigenheim) | B11: 480000 | C11: 0.8 | D11: 0.02 | E11: 2021 | F11: 46 | G11: =B11*C11*D11 -> 7680 | H11: =G11*(2026-E11) -> 38400
A12: Steinertgasse 5B (JW) | B12: 37500 | C12: 0.8 | D12: 0.02 | E12: 2017 | F12: 42 | G12: =B12*C12*D12 -> 600 | H12: =G12*(2026-E12) -> 5400
A13: Stauffenbergstr. 30 (50%) | B13: 325000 | C13: 0.8 | D13: 0.02 | E13: 2017 | F13: 42 | G13: =B13*C13*D13 -> 5200 | H13: =G13*(2026-E13) -> 46800
A14: Stauffenbergstr. 33 (50%) | B14: 195000 | C14: 0.8 | D14: 0.02 | E14: 2017 | F14: 42 | G14: =B14*C14*D14 -> 3120 | H14: =G14*(2026-E14) -> 28080
A15: Silcherstr. 4 Wng. 8 (50%) | B15: 79500 | C15: 0.8 | D15: 0.02 | E15: 2022 | F15: 47 | G15: =B15*C15*D15 -> 1272 | H15: =G15*(2026-E15) -> 5088
... A17: Stauffenbergring 28 (50%) | B17: 352500 | C17: 0.8 | D17: 0.03 | E17: 2024 | F17: 50 | G17: =B17*C17*D17 -> 8460 | H17: =G17*(2026-E17) -> 16920
A18: SUMME | G18: =SUM(G4:G17) -> 50908 | H18: =SUM(H4:H17) -> 352432
A21: ZINSAUFWAND (für Steuererklärung)
A23: Jährlicher Zinsaufwand Immobilien (anteilig): | C23: =2_Darlehen!N26 -> 57383.071
A24: Jährliche AfA gesamt: | C24: =G18 -> 50908
A26: Steuerliche Absetzungen gesamt: | C26: =C23+C24 -> 108291.07

Sheet 6_Liquiditaet
A1: LIQUIDITÄTSÜBERSICHT - Stand 22.01.2026
A3: Bank | B3: Kontotyp | C3: IBAN | D3: Kontoinhaber | E3: Saldo
A4: KSK Ostalb | B4: Girokonto | C4: DE11 6145 0050 0805 3935 03 | D4: Felix Wanner | E4: 518.02
A5: KSK Ostalb | B5: Girokonto | C5: DE85 6145 0050 1000 1667 16 | D5: Felix Wanner | E5: 123085.8
A6: KSK Ostalb | B6: Girokonto | C6: DE05 6145 0050 1001 2152 71 | D6: Felix Wanner | E6: 4625.73
A7: KSK Ostalb | B7: Geldmarktkonto | C7: DE87 6145 0050 1100 3364 46 | D7: Felix Wanner | E7: 585.91
A8: KSK Ostalb | B8: Geldmarktkonto | C8: DE15 6145 0050 1100 3390 03 | D8: Felix Wanner | E8: 27.14
A9: ING | B9: Girokonto | C9: DE84 5001 0517 5415 3766 66 | D9: Felix Otto Wanner | E9: 1668.18
A10: N26 | B10: Hauptkonto | C10: DE20 1001 1001 2620 0670 36 | D10: Felix Otto Wanner | E10: 526.83
A11: Raiba Rosenstein | B11: Kontokorrent | C11: DE96 6136 1722 0087 2590 01 | D11: Felix Wanner | E11: 2967.34
A12: Raiba Rosenstein | B12: Kontokorrent | C12: DE46 6136 1722 0087 2590 28 | D12: Felix Wanner | E12: 163.46
A13: Raiba Rosenstein | B13: Kontokorrent | C13: DE24 6136 1722 0087 2590 36 | D13: Felix Wanner | E13: 1703.4
A14: Raiba Rosenstein | B14: Kontokorrent | C14: DE02 6136 1722 0087 2590 44 | D14: Felix Wanner | E14: 2573.99
A15: Raiba Rosenstein | B15: Kontokorrent | C15: DE77 6136 1722 0087 2590 52 | D15: Felix Wanner | E15: 1654.89
... A24: VB Südwestfalen | B24: Kontokorrent PV | C24: DE65 4476 1534 0016 1701 00 | D24: Felix Otto Wanner | E24: 5706.87
A25: SUMME LIQUIDE MITTEL | E25: =SUM(E4:E24) -> 174482.13
A28: WEITERE VERMÖGENSWERTE (aus Bankübersicht)
A30: Union Investment Depot | B30: 10194709 | E30: 39027.32
A31: Schwäbisch Hall BSV | B31: 24402962J01 | E31: 10544.68
A32: Schwäbisch Hall BSV | B32: 24402962J02 | E32: 10009.8
A33: Schwäbisch Hall BSV | B33: 24402962J04 | E33: 27944.66
A34: SUMME Depot/BSV | E34: =SUM(E30:E33) -> 87526.46
A37: MONATLICHER LIQUIDITÄTSBEDARF
A39: Darlehensraten Immobilien (anteilig): | C39: =2_Darlehen!I26 -> 12215.81
A40: Darlehensraten PV (anteilig): | C40: ='3_PV-Anlagen'!K5 -> 3914.83
A41: Instandhaltungsrücklage: | C41: =1_Immobilien!W19 -> 1707.4833
A42: GESAMT Ausgaben/Monat: | C42: =C39+C40+C41 -> 17838.123
A44: Mieteinnahmen (anteilig): | C44: =1_Immobilien!I19 -> 15011.87
A45: PV-Einnahmen (anteilig): | C45: ='3_PV-Anlagen'!J5 -> 4100
A46: GESAMT Einnahmen/Monat: | C46: =C44+C45 -> 19111.87
A48: NETTO-LIQUIDITÄT/Monat: | C48: =C46-C42 -> 1273.7467

Sheet 7_Zinssensitivitaet
A1: ZINSSENSITIVITÄTS-ANALYSE - Refinanzierungsszenarien
A3: Objekt | B3: Restschuld | C3: Ende Zinsbind. | D3: Aktueller Zins | E3: Aktuelle Rate | F3: Rate bei 3% | G3: Rate bei 4% | H3: Rate bei 5% | I3: Mehrkosten 4% vs. aktuell
A4: Gmünder Str. 11 (Raiba) | B4: 87007.64 | C4: 30.11.2025 | D4: 0.0195 | E4: 400 | F4: =PMT(0.03/12,120,-B4) -> 840.15225 | G4: =PMT(0.04/12,120,-B4) -> 880.91005 | H4: =PMT(0.05/12,120,-B4) -> 922.85102 | I4: =(G4-E4)*12 -> 5770.9206
A5: Jakob-Uhlmann 6 DG (Raiba) | B5: 17093.18 | C5: 30.06.2026 | D5: 0.0225 | E5: 137.9 | F5: =PMT(0.03/12,120,-B5) -> 165.05302 | G5: =PMT(0.04/12,120,-B5) -> 173.06014 | H5: =PMT(0.05/12,120,-B5) -> 181.29969 | I5: =(G5-E5)*12 -> 421.92164
A6: Jakob-Uhlmann 6 DG (BSV) | B6: 29955 | C6: 30.06.2026 | D6: 0.0225 | E6: 145 | F6: =PMT(0.03/12,120,-B6) -> 289.24771 | G6: =PMT(0.04/12,120,-B6) -> 303.27981 | H6: =PMT(0.05/12,120,-B6) -> 317.71925 | I6: =(G6-E6)*12 -> 1899.3577
A7: Schillerstraße 1 (Raiba) | B7: 19932.82 | C7: 30.06.2026 | D7: 0.0225 | E7: 135 | F7: =PMT(0.03/12,120,-B7) -> 192.47279 | G7: =PMT(0.04/12,120,-B7) -> 201.81011 | H7: =PMT(0.05/12,120,-B7) -> 211.41848 | I7: =(G7-E7)*12 -> 801.72134
A8: Schillerstraße 1 (BSV) | B8: 29955 | C8: 30.06.2026 | D8: 0.0225 | E8: 135 | F8: =PMT(0.03/12,120,-B8) -> 289.24771 | G8: =PMT(0.04/12,120,-B8) -> 303.27981 | H8: =PMT(0.05/12,120,-B8) -> 317.71925 | I8: =(G8-E8)*12 -> 2019.3577
A9: Rembrandtweg 8 (Raiba 1) | B9: 72225.55 | C9: 30.07.2026 | D9: 0.0195 | E9: 465.3 | F9: =PMT(0.03/12,120,-B9) -> 697.41529 | G9: =PMT(0.04/12,120,-B9) -> 731.24858 | H9: =PMT(0.05/12,120,-B9) -> 766.06402 | I9: =(G9-E9)*12 -> 3191.3829
A10: Eutighofer Str. 22 (Raiba 1) | B10: 132207 | C10: 30.08.2026 | D10: 0.018 | E10: 805 | F10: =PMT(0.03/12,120,-B10) -> 1276.6006 | G10: =PMT(0.04/12,120,-B10) -> 1338.5316 | H10: =PMT(0.05/12,120,-B10) -> 1402.2604 | I10: =(G10-E10)*12 -> 6402.3792
A11: Eutighofer Str. 22 (Raiba 2) | B11: 59918.22 | C11: 30.11.2026 | D11: 0.012 | E11: 880 | F11: =PMT(0.03/12,120,-B11) -> 578.57479 | G11: =PMT(0.04/12,120,-B11) -> 606.64285 | H11: =PMT(0.05/12,120,-B11) -> 635.52569 | I11: =(G11-E11)*12 -> -3280.2858
A12: Rembrandtweg 8 (Raiba 2) | B12: 30288.59 | C12: 30.11.2026 | D12: 0.012 | E12: 440 | F12: =PMT(0.03/12,120,-B12) -> 292.46888 | G12: =PMT(0.04/12,120,-B12) -> 306.65725 | H12: =PMT(0.05/12,120,-B12) -> 321.25749 | I12: =(G12-E12)*12 -> -1600.113
A13: Stauffenbergstr. 30 (50%) | B13: 247322.9 | C13: 30.03.2027 | D13: 0.021 | E13: 1410 | F13: =PMT(0.03/12,120,-B13) -> 2388.1683 | G13: =PMT(0.04/12,120,-B13) -> 2504.0241 | H13: =PMT(0.05/12,120,-B13) -> 2623.2431 | I13: =(G13-E13)*12 -> 13128.289
A14: Stauffenbergstr. 33 (50%) | B14: 148027.53 | C14: 30.03.2027 | D14: 0.021 | E14: 850 | F14: =PMT(0.03/12,120,-B14) -> 1429.3649 | G14: =PMT(0.04/12,120,-B14) -> 1498.7068 | H14: =PMT(0.05/12,120,-B14) -> 1570.0616 | I14: =(G14-E14)*12 -> 7784.4813
A15: Steinertgasse 5B (JW) | B15: 33406.63 | C15: 30.04.2027 | D15: 0.019 | E15: 95 | F15: =PMT(0.03/12,120,-B15) -> 322.57691 | G15: =PMT(0.04/12,120,-B15) -> 338.22589 | H15: =PMT(0.05/12,120,-B15) -> 354.32914 | I15: =(G15-E15)*12 -> 2918.7106
A16: Stauffenbergstr. 30+33 (50%) | B16: 122967 | C16: 30.06.2027 | D16: 0.0198 | E16: 522.5 | F16: =PMT(0.03/12,120,-B16) -> 1187.3785 | G16: =PMT(0.04/12,120,-B16) -> 1244.9811 | H16: =PMT(0.05/12,120,-B16) -> 1304.2558 | I16: =(G16-E16)*12 -> 8669.7731
A17: SUMME | B17: =SUM(B4:B16) -> 1030307.1 | E17: =SUM(E4:E16) -> 6420.7 | F17: =SUM(F4:F16) -> 9948.7217 | G17: =SUM(G4:G16) -> 10431.358 | H17: =SUM(H4:H16) -> 10928.005 | I17: =SUM(I4:I16) -> 48127.897
A20: ZUSAMMENFASSUNG ZINSRISIKO
A22: Refinanzierungsvolumen 2025-2027: | C22: =B17 -> 1030307.1
A23: Aktuelle Ratenbelastung/Monat: | C23: =E17 -> 6420.7
A24: Rate bei 4% Refinanzierung/Monat: | C24: =G17 -> 10431.358
A25: JÄHRLICHE MEHRKOSTEN bei 4%: | C25: =I17 -> 48127.897

Sheet 8_Tilgungsprognose
A1: TILGUNGSPROGNOSE - Schuldenentwicklung 2026-2036
A3: Jahr | B3: 2026 | C3: 2027 | D3: 2028 | E3: 2029 | F3: 2030 | G3: 2031 | H3: 2032 | I3: 2033 | J3: 2034 | K3: 2035 | L3: 2036
A4: Schulden Immobilien | B4: 2150000 | C4: 2065000 | D4: 1980000 | E4: 1895000 | F4: 1810000 | G4: 1725000 | H4: 1640000 | I4: 1555000 | J4: 1470000 | K4: 1385000 | L4: 1300000
A5: Schulden PV | B5: 830000 | C5: 785000 | D5: 740000 | E5: 695000 | F5: 650000 | G5: 605000 | H5: 560000 | I5: 515000 | J5: 470000 | K5: 425000 | L5: 380000
A6: Schulden Gesamt | B6: =B4+B5 -> 2980000 | C6: =C4+C5 -> 2850000 | D6: =D4+D5 -> 2720000 | E6: =E4+E5 -> 2590000 | F6: =F4+F5 -> 2460000 | G6: =G4+G5 -> 2330000 | H6: =H4+H5 -> 2200000 | I6: =I4+I5 -> 2070000 | ... L6: =L4+L5 -> 1680000
A7: Eigenkapital (geschätzt) | B7: =5500000-B6 -> 2520000 | C7: =5500000-C6 -> 2650000 | D7: =5500000-D6 -> 2780000 | E7: =5500000-E6 -> 2910000 | F7: =5500000-F6 -> 3040000 | G7: =5500000-G6 -> 3170000 | H7: =5500000-H6 -> 3300000 | I7: =5500000-I6 -> 3430000 | ... L7: =5500000-L6 -> 3820000

Sheet 9_BSV_Tilgungsersatz
A1: BAUSPARVERTRÄGE & TILGUNGSERSATZPRODUKTE
A3: Produkt | B3: Vertragsnummer | C3: Zugeordnetes Darlehen | D3: Aktuelles Guthaben | E3: Sparrate/Mon | F3: Zielkapital | G3: Erreichungsgrad
A4: Schwäbisch Hall BSV Sparphase | B4: 24402962J01 | C4: Jakob-Uhlmann 6 DG | D4: 10544.68 | E4: 145 | F4: 29955 | G4: =D4/F4 -> 0.35201736
A5: Schwäbisch Hall BSV Sparphase | B5: 24402962J02 | C5: Schillerstraße 1 | D5: 10009.8 | E5: 135 | F5: 29955 | G5: =D5/F5 -> 0.33416124
A6: Schwäbisch Hall BSV Sparphase | B6: 24402962J04 | C6: Gmünder Str. 11 | D6: 27944.66 | E6: 386 | F6: 50000 | G6: =D6/F6 -> 0.5588932
A7: Union Investment Depot | B7: 10194709 | C7: Gmünder Str. 11 (100k) | D7: 39027.32 | E7: 250 | F7: 100000 | G7: =D7/F7 -> 0.3902732
A8: R+V Fondspolice | B8: 07/055034516 | C8: PV Stade (344k) | D8: 158000 | E8: 650 | F8: 344000 | G8: =D8/F8 -> 0.45930233
A9: SUMME | D9: =SUM(D4:D8) -> 245526.46 | E9: =SUM(E4:E8) -> 1566 | F9: =SUM(F4:F8) -> 553910

Sheet 10_Dashboard
A1: INVESTOREN-DASHBOARD
A2: Stand: 22.01.2026
A4: VERMÖGENSÜBERSICHT
A6: Verkehrswert Immobilien (anteilig): | C6: =1_Immobilien!K19 -> 4797667
A7: Wert PV-Anlagen (anteilig): | C7: ='3_PV-Anlagen'!N5 -> 734000
A8: Liquide Mittel: | C8: =6_Liquiditaet!E25 -> 174482.13
A9: Depot/BSV/Fonds: | C9: =9_BSV_Tilgungsersatz!D9 -> 245526.46
A10: GESAMTVERMÖGEN: | C10: =C6+C7+C8+C9 -> 5951675.6
A12: SCHULDENÜBERSICHT
A14: Darlehen Immobilien (anteilig): | C14: =2_Darlehen!H26 -> 2582952.2
A15: Darlehen PV (anteilig): | C15: ='3_PV-Anlagen'!I5 -> 825882.73
A16: GESAMTSCHULDEN: | C16: =C14+C15 -> 3408834.9
A18: NETTOVERMÖGEN (EIGENKAPITAL): | C18: =C10-C16 -> 2542840.7
A20: WICHTIGE KENNZAHLEN
A22: Loan-to-Value (LTV): | C22: =C16/(C6+C7) -> 0.61624008
A23: Eigenkapitalquote: | C23: =C18/C10 -> 0.42724787
A24: Brutto-Mietrendite Immobilien: | C24: =1_Immobilien!R19 -> 0.037547925
A25: Anzahl Wohneinheiten (anteilig): | C25: =1_Immobilien!G19 -> 29.5
A26: Wohnfläche m² (anteilig): | C26: =1_Immobilien!H19 -> 2048.98
A27: PV-Leistung kWp (anteilig): | C27: ='3_PV-Anlagen'!D5 -> 740
A29: MONATLICHER CASHFLOW
A31: Mieteinnahmen (anteilig): | C31: =1_Immobilien!I19 -> 15011.87
A32: PV-Einnahmen (anteilig): | C32: ='3_PV-Anlagen'!J5 -> 4100
A33: Darlehensraten Immobilien: | C33: =-2_Darlehen!I26 -> -12215.81
A34: Darlehensraten PV: | C34: =-'3_PV-Anlagen'!K5 -> -3914.83
A35: Instandhaltungsrücklage: | C35: =-1_Immobilien!W19 -> -1707.4833
A36: NETTO-CASHFLOW/MONAT: | C36: =C31+C32+C33+C34+C35 -> 1273.7467
A37: NETTO-CASHFLOW/JAHR: | C37: =C36*12 -> 15284.96
A39: STEUERLICHE ABSETZUNGEN/JAHR
A41: AfA Immobilien: | C41: =5_AfA_Steuer!G18 -> 50908
A42: Zinsaufwand: | C42: =5_AfA_Steuer!C22 -> 0
A43: GESAMT steuerlich absetzbar: | C43: =C41+C42 -> 50908
A45: RISIKO-HINWEISE
A47: Refinanzierungsvolumen 2025-2027: | C47: =7_Zinssensitivitaet!B17 -> 1030307.1
A48: Mehrkosten bei 4% Refinanzierung/Jahr: | C48: =7_Zinssensitivitaet!I17 -> 48127.897
A49: Mietpotenzial/Monat (nicht ausgeschöpft): | C49: =1_Immobilien!V19 -> 2828.775
A50: Leerstand aktuell: | C50: 3 WE (Eutighofer, Oberbettringer, Stauffenbergstr.)
